libtiepie/__init__.py
libtiepie/api.py
libtiepie/const.py
libtiepie/device.py
libtiepie/devicelist.py
libtiepie/devicelistitem.py
libtiepie/exceptions.py
libtiepie/generator.py
libtiepie/library.py
libtiepie/network.py
libtiepie/networkservers.py
libtiepie/object.py
libtiepie/objectlist.py
libtiepie/oscilloscope.py
libtiepie/oscilloscopechannel.py
libtiepie/oscilloscopechannels.py
libtiepie/oscilloscopechanneltrigger.py
libtiepie/oscilloscopechanneltriggerhystereses.py
libtiepie/oscilloscopechanneltriggerlevels.py
libtiepie/oscilloscopechanneltriggertimes.py
libtiepie/oscilloscopetrigger.py
libtiepie/server.py
libtiepie/triggerinput.py
libtiepie/triggerinputs.py
libtiepie/triggeroutput.py
libtiepie/triggeroutputs.py
libtiepie/types.py
libtiepie/utils.py
libtiepie/_platform/__init__.py
libtiepie/_platform/_linux/__init__.py
libtiepie/_platform/_linux/amd64/libtiepie-core.so.0
libtiepie/_platform/_linux/amd64/libtiepie-core.so.0.17.0
libtiepie/_platform/_linux/amd64/libtiepie-hw.so
libtiepie/_platform/_linux/amd64/libtiepie-hw.so.1
libtiepie/_platform/_linux/amd64/libtiepie-hw.so.1.2.5
libtiepie/_platform/_linux/amd64/libtiepie-m.so.0
libtiepie/_platform/_linux/amd64/libtiepie-m.so.0.38.5
libtiepie/_platform/_linux/amd64/libtiepie-nw.so.0
libtiepie/_platform/_linux/amd64/libtiepie-nw.so.0.16.9
libtiepie/_platform/_linux/amd64/libtiepie-tp.so.0
libtiepie/_platform/_linux/amd64/libtiepie-tp.so.0.8.1
libtiepie/_platform/_linux/amd64/libtiepie-usb.so.0
libtiepie/_platform/_linux/amd64/libtiepie-usb.so.0.8.5
libtiepie/_platform/_linux/arm64/libtiepie-core.so.0
libtiepie/_platform/_linux/arm64/libtiepie-core.so.0.17.0
libtiepie/_platform/_linux/arm64/libtiepie-hw.so
libtiepie/_platform/_linux/arm64/libtiepie-hw.so.1
libtiepie/_platform/_linux/arm64/libtiepie-hw.so.1.2.5
libtiepie/_platform/_linux/arm64/libtiepie-m.so.0
libtiepie/_platform/_linux/arm64/libtiepie-m.so.0.38.5
libtiepie/_platform/_linux/arm64/libtiepie-nw.so.0
python_libtiepie_bi-1.2.5.1.dist-info/LICENSE
python_libtiepie_bi-1.2.5.1.dist-info/METADATA
python_libtiepie_bi-1.2.5.1.dist-info/WHEEL
python_libtiepie_bi-1.2.5.1.dist-info/top_level.txt
python_libtiepie_bi-1.2.5.1.dist-info/zip-safe
python_libtiepie_bi-1.2.5.1.dist-info/RECORD
